data_agora/__init__.py
data_agora/agora.py
data_agora/core/__init__.py
data_agora/core/intrinsic_evaluators.py
data_agora/core/llms/base.py
data_agora/core/llms/litellm.py
data_agora/core/llms/local_vllm.py
data_agora/core/llms/openai.py
data_agora/core/llms/test.py
data_agora/core/llms/vllm.py
data_agora/core/parsers.py
data_agora/core/prompt_loaders.py
data_agora/core/validators.py
data_agora/serve.py
data_agora-0.1.2.dist-info/METADATA
data_agora-0.1.2.dist-info/WHEEL
data_agora-0.1.2.dist-info/RECORD
