Metadata-Version: 2.1
Name: data-agora
Version: 0.1.2
Summary: 
License: MIT
Author: Juyoung Suk
Author-email: juyoung@kaist.ac.kr
Requires-Python: >=3.10,<4.0
Classifier: License :: OSI Approved :: MIT License
Classifier: Programming Language :: Python :: 3
Classifier: Programming Language :: Python :: 3.10
Classifier: Programming Language :: Python :: 3.11
Classifier: Programming Language :: Python :: 3.12
Classifier: Programming Language :: Python :: 3.13
